drf_viewset_scenarios-1.0.0.dist-info/METADATA
drf_viewset_scenarios-1.0.0.dist-info/WHEEL
drf_viewset_scenarios-1.0.0.dist-info/entry_points.txt
drf_viewset_scenarios-1.0.0.dist-info/licenses/LICENSE
viewset_scenarios/__init__.py
viewset_scenarios/action_type.py
viewset_scenarios/conditions.py
viewset_scenarios/exceptions.py
viewset_scenarios/scenarios.py
viewset_scenarios/utils.py
viewset_scenarios/viewset.py
drf_viewset_scenarios-1.0.0.dist-info/RECORD
