Metadata-Version: 2.1
Name: drf-viewset-scenarios
Version: 1.0.0
Summary: A Django REST Framework package that provides a flexible way to manage different serializers and paginators in your ViewSets based on defined scenarios.
Author-Email: Jancel <ja.alvarezgom@gmail.com>
License: MIT
Classifier: Programming Language :: Python :: 3.10
Classifier: Programming Language :: Python :: 3.11
Classifier: Programming Language :: Python :: 3.12
Classifier: Development Status :: 5 - Production/Stable
Classifier: Topic :: Software Development :: Libraries :: Python Modules
Classifier: Topic :: Software Development :: Libraries :: Application Frameworks
Classifier: Topic :: Software Development :: Libraries
Classifier: Topic :: Software Development
Classifier: Topic :: Utilities
Classifier: Typing :: Typed
Project-URL: Homepage, https://github.com/jalvarezgom/drf-viewset-scenarios
Project-URL: Issues, https://github.com/jalvarezgom/drf-viewset-scenarios/issues
Requires-Python: >=3.10
Requires-Dist: djangorestframework>=3.15.2
